{
    "users": [
        {
            "id": "1",
            "nome": "Marina Paiva",
            "avatar": "https://static.vecteezy.com/system/resources/thumbnails/027/951/136/small/manager-woman-3d-avatar-character-illustrations-png.png"
        }
    ],
    "estudos": [
        {
            "id": "1",
            "nome": "Estudo 1",
            "imagens": [
                {
                    "id": "1",
                    "link": "https://clinicatemplum.com.br/wp-content/uploads/2021/09/raio-x-templum.jpg"
                },
                {
                    "id": "2",
                    "link": "https://clinicatemplum.com.br/wp-content/uploads/2021/09/raio-x-templum.jpg"
                },
                {
                    "id": "3",
                    "link": "https://clinicatemplum.com.br/wp-content/uploads/2021/09/raio-x-templum.jpg"
                },
                {
                    "id": "4",
                    "link": "https://clinicatemplum.com.br/wp-content/uploads/2021/09/raio-x-templum.jpg"
                },
                {
                    "id": "5",
                    "link": "https://clinicatemplum.com.br/wp-content/uploads/2021/09/raio-x-templum.jpg"
                },
                {
                    "id": "6",
                    "link": "https://clinicatemplum.com.br/wp-content/uploads/2021/09/raio-x-templum.jpg"
                },
                {
                    "id": "7",
                    "link": "https://clinicatemplum.com.br/wp-content/uploads/2021/09/raio-x-templum.jpg"
                },
                {
                    "id": "8",
                    "link": "https://clinicatemplum.com.br/wp-content/uploads/2021/09/raio-x-templum.jpg"
                },
                {
                    "id": "9",
                    "link": "https://clinicatemplum.com.br/wp-content/uploads/2021/09/raio-x-templum.jpg"
                },
                {
                    "id": "10",
                    "link": "https://clinicatemplum.com.br/wp-content/uploads/2021/09/raio-x-templum.jpg"
                },
                {
                    "id": "11",
                    "link": "https://clinicatemplum.com.br/wp-content/uploads/2021/09/raio-x-templum.jpg"
                },
                {
                    "id": "12",
                    "link": "https://clinicatemplum.com.br/wp-content/uploads/2021/09/raio-x-templum.jpg"
                },
                {
                    "id": "13",
                    "link": "https://clinicatemplum.com.br/wp-content/uploads/2021/09/raio-x-templum.jpg"
                },
                {
                    "id": "14",
                    "link": "https://clinicatemplum.com.br/wp-content/uploads/2021/09/raio-x-templum.jpg"
                }
            ],
            "status": "pendente",
            "laudoId": null
        },
        {
            "id": "2",
            "nome": "Estudo 2",
            "imagens": [
                
                {
                    "id": "2",
                    "link": "https://clinicatemplum.com.br/wp-content/uploads/2021/09/raio-x-templum.jpg"
                },
                {
                    "id": "3",
                    "link": "https://clinicatemplum.com.br/wp-content/uploads/2021/09/raio-x-templum.jpg"
                },
                {
                    "id": "4",
                    "link": "https://clinicatemplum.com.br/wp-content/uploads/2021/09/raio-x-templum.jpg"
                },
                {
                    "id": "5",
                    "link": "https://clinicatemplum.com.br/wp-content/uploads/2021/09/raio-x-templum.jpg"
                },
                {
                    "id": "6",
                    "link": "https://clinicatemplum.com.br/wp-content/uploads/2021/09/raio-x-templum.jpg"
                }
            ],
            "status": "pendente",
            "laudoId": null
        },
        {
            "id": "3",
            "nome": "Estudo 3",
            "imagens": [
                {
                    "id": "1",
                    "link": "https://clinicatemplum.com.br/wp-content/uploads/2021/09/raio-x-templum.jpg"
                },
                {
                    "id": "2",
                    "link": "https://clinicatemplum.com.br/wp-content/uploads/2021/09/raio-x-templum.jpg"
                },
                {
                    "id": "3",
                    "link": "https://clinicatemplum.com.br/wp-content/uploads/2021/09/raio-x-templum.jpg"
                },
                {
                    "id": "4",
                    "link": "https://clinicatemplum.com.br/wp-content/uploads/2021/09/raio-x-templum.jpg"
                },
                {
                    "id": "5",
                    "link": "https://clinicatemplum.com.br/wp-content/uploads/2021/09/raio-x-templum.jpg"
                },
                {
                    "id": "6",
                    "link": "https://clinicatemplum.com.br/wp-content/uploads/2021/09/raio-x-templum.jpg"
                }
            ],
            "status": "laudado",
            "laudoId": "1"
        },
        {
            "id": "4",
            "nome": "Estudo 4",
            "imagens": [
                {
                    "id": "1",
                    "link": "https://clinicatemplum.com.br/wp-content/uploads/2021/09/raio-x-templum.jpg"
                },
                {
                    "id": "2",
                    "link": "https://clinicatemplum.com.br/wp-content/uploads/2021/09/raio-x-templum.jpg"
                },
                {
                    "id": "3",
                    "link": "https://clinicatemplum.com.br/wp-content/uploads/2021/09/raio-x-templum.jpg"
                },
                {
                    "id": "4",
                    "link": "https://clinicatemplum.com.br/wp-content/uploads/2021/09/raio-x-templum.jpg"
                },
                {
                    "id": "5",
                    "link": "https://clinicatemplum.com.br/wp-content/uploads/2021/09/raio-x-templum.jpg"
                },
                {
                    "id": "6",
                    "link": "https://clinicatemplum.com.br/wp-content/uploads/2021/09/raio-x-templum.jpg"
                }
            ],
            "status": "laudado",
            "laudoId": "2"
        }
    ],
    "laudos": [
        {
            "id": "1",
            "medico": {
                "id": "1",
                "nome": "Carlos Maciel Arantes",
                "avatar": "https://www.svgrepo.com/show/81103/avatar.svg"
            }
        },
        {
            "id": "2",
            "medico": {
                "id": "1",
                "nome": "Carlos Maciel Arantes",
                "avatar": "https://www.svgrepo.com/show/81103/avatar.svg"
            }
        }
    ],
    "achados": [
        {   
            "id": "1",
            "laudoId": "1",
            "imagemId": "1",
            "titulo": "Achado 1",
            "orgao": "Coração",
            "sistema": "Cardiovascular",
            "patologias": [
                "Miocardiopatia dilatada",
                "Valvopatia"
            ],
            "severidade": "grave",
            "observacoes": "Laudo concluído."
        }
    ]
}